Demux/demux.v
module demux (
   input d,En,
   input [1:0]s,
   output reg [3:0]o
);
    always @(*) begin
        if (En==1) begin
            case (s)
                2'b00 : o[0] = d; 
                2'b01 : o[1] = d; 
                2'b10 : o[2] = d; 
                2'b11 : o[3] = d; 
                default: o = 4'bxxxx;
            endcase
        end
        else begin
            o = 4'bxxxx;
        end
    end
endmodule

Demux/demux_tb.v
module demux_tb();
    reg d,En;
    reg [1:0]s;
    wire [3:0]o;

   demux dut(d,En,s,o);
   initial begin
    $dumpfile("demux.vcd");
    $dumpvars(0,demux_tb);
   for (integer i=0;i<2;i=i+1) begin
    En = i;
    if(En==1)begin
        d = 1;
        for (integer j=0;j<4;j=j+1) begin
            s = j; #10;
        end
       #10; d = 0;
        for (integer k=0;k<4;k=k+1) begin
            s = k; #10;
        end
    end
   else begin
    #10;
   end
   end
   $display("Test done");
   #10 $finish;
   end 
endmodule

Demux/demux.vcd
$date
	Mon Jun 09 16:13:45 2025
$end
$version
	Icarus Verilog
$end
$timescale
	1s
$end
$scope module demux_tb $end
$var wire 4 ! o [3:0] $end
$var reg 1 " En $end
$var reg 1 # d $end
$var reg 2 $ s [1:0] $end
$scope module dut $end
$var wire 1 " En $end
$var wire 1 # d $end
$var wire 2 % s [1:0] $end
$var reg 4 & o [3:0] $end
$upscope $end
$scope begin $ivl_for_loop0 $end
$var integer 32 ' i [31:0] $end
$scope begin $ivl_for_loop1 $end
$var integer 32 ( j [31:0] $end
$upscope $end
$scope begin $ivl_for_loop2 $end
$var integer 32 ) k [31:0] $end
$upscope $end
$upscope $end
$upscope $end
$enddefinitions $end
$comment Show the parameter values. $end
$dumpall
$end
#0
$dumpvars
bx )
bx (
b0 '
bx &
bx %
bx $
x#
0"
bx !
$end
#10
bx1 !
bx1 &
b0 $
b0 %
b0 (
1#
1"
b1 '
#20
bx11 !
bx11 &
b1 $
b1 %
b1 (
#30
bx111 !
bx111 &
b10 $
b10 %
b10 (
#40
b1111 !
b1111 &
b11 $
b11 %
b11 (
#50
b100 (
#60
b1110 !
b1110 &
b0 $
b0 %
b0 )
0#
#70
b1100 !
b1100 &
b1 $
b1 %
b1 )
#80
b1000 !
b1000 &
b10 $
b10 %
b10 )
#90
b0 !
b0 &
b11 $
b11 %
b11 )
#100
b10 '
b100 )
