GrayConverter/gray.v
module gray(
    input [7:0] in,
    output reg [7:0]o
);
    always @(*) begin
    o[7] = in[7];
        for (integer i=6;i>-1;i=i-1) begin
            o[i] = in[i+1]^in[i];
        end
    end
endmodule

GrayConverter/gray_tb.v
module gray_tb();
   reg [7:0]in;
   wire [7:0]o;
gray dut (in,o);

initial begin
$dumpfile("gray.vcd");
$dumpvars(0,gray_tb);
in = 8'b00000000; #10;
in = 8'b00000001; #10;
in = 8'b00000010; #10;
in = 8'b00000011; #10;
in = 8'b00000100; #10;
in = 8'b00000101; #10;
in = 8'b00000110; #10;
in = 8'b00000111; #10;

$display("Test done");
 $finish;
end
endmodule

GrayConverter/gray.vcd
$date
	Mon Jun 09 17:51:51 2025
$end
$version
	Icarus Verilog
$end
$timescale
	1s
$end
$scope module gray_tb $end
$var wire 8 ! o [7:0] $end
$var reg 8 " in [7:0] $end
$scope module dut $end
$var wire 8 # in [7:0] $end
$var reg 8 $ o [7:0] $end
$scope begin $ivl_for_loop0 $end
$var integer 32 % i [31:0] $end
$upscope $end
$upscope $end
$upscope $end
$enddefinitions $end
$comment Show the parameter values. $end
$dumpall
$end
#0
$dumpvars
b11111111111111111111111111111111 %
b0 $
b0 #
b0 "
b0 !
$end
#10
b1 !
b1 $
b11111111111111111111111111111111 %
b1 "
b1 #
#20
b11 !
b11 $
b11111111111111111111111111111111 %
b10 "
b10 #
#30
b10 !
b10 $
b11111111111111111111111111111111 %
b11 "
b11 #
#40
b110 !
b110 $
b11111111111111111111111111111111 %
b100 "
b100 #
#50
b111 !
b111 $
b11111111111111111111111111111111 %
b101 "
b101 #
#60
b101 !
b101 $
b11111111111111111111111111111111 %
b110 "
b110 #
#70
b100 !
b100 $
b11111111111111111111111111111111 %
b111 "
b111 #
